advancedbot/__init__.py
advancedbot/telegrambot.py
advancedbot/components/__init__.py
advancedbot/components/exceptions/__init__.py
advancedbot/components/exceptions/telegramboterror.py
advancedbot/components/locales/__init__.py
advancedbot/components/locales/localemanager.py
advancedbot/components/logs/__init__.py
advancedbot/components/logs/botlogger.py
advancedbot/components/logs/exceptions/__init__.py
advancedbot/components/logs/exceptions/botloggererror.py
advancedbot/components/logs/exceptions/wrongloglevelerror.py
advancedbot/components/messaging/__init__.py
advancedbot/components/messaging/messagesender.py
advancedbot/components/models/__init__.py
advancedbot/components/models/documentlink.py
advancedbot/components/models/user.py
advancedbot/components/role_managing/__init__.py
advancedbot/components/role_managing/roleauth.py
advancedbot/components/role_managing/exceptions/__init__.py
advancedbot/components/role_managing/exceptions/alreadyloggederror.py
advancedbot/components/role_managing/exceptions/passworderror.py
advancedbot/components/role_managing/exceptions/roleerror.py
advancedbot/components/routing/__init__.py
advancedbot/components/routing/router.py
advancedbot/components/routing/routes/__init__.py
advancedbot/components/routing/routes/commandroute.py
advancedbot/components/routing/routes/documentroute.py
advancedbot/components/routing/routes/imageroute.py
advancedbot/components/routing/routes/messageroute.py
advancedbot/components/routing/routes/route.py
advancedbot/components/state_managing/__init__.py
advancedbot/components/state_managing/statemanager.py
advancedbot/components/state_managing/exceptions/__init__.py
advancedbot/components/state_managing/exceptions/stateerror.py
advancedbot/components/storage_managing/__init__.py
advancedbot/components/storage_managing/localjsonstorage.py
advancedbot/components/storage_managing/mongodbstorage.py
advancedbot/components/storage_managing/storage.py
advanced_telegram_bot-0.2.1.dist-info/LICENSE
advanced_telegram_bot-0.2.1.dist-info/METADATA
advanced_telegram_bot-0.2.1.dist-info/WHEEL
advanced_telegram_bot-0.2.1.dist-info/top_level.txt
advanced_telegram_bot-0.2.1.dist-info/RECORD
