Metadata-Version: 2.1
Name: advanced-telegram-bot
Version: 0.2.1
Summary: Python library containing utils for telegram bots
Home-page: https://github.com/sdallaboratory/advanced-telegram-bot
Author: minish144 & usual-one
Author-email: varlamow.col@yahoo.com
License: UNKNOWN
Platform: UNKNOWN
Classifier: Programming Language :: Python :: 3
Classifier: License :: OSI Approved :: MIT License
Classifier: Operating System :: OS Independent
Requires-Python: >=3.6
Requires-Dist: pymongo
Requires-Dist: python-telegram-bot
Requires-Dist: decorator
